qrl_graph/__init__.py
qrl_graph/utils.py
qrl_graph/agent/__init__.py
qrl_graph/agent/ga.py
qrl_graph/agent/gpn.py
qrl_graph/agent/pg.py
qrl_graph/graph_env/__init__.py
qrl_graph/graph_env/graph.py
qrl_graph-0.0.13.dist-info/LICENSE
qrl_graph-0.0.13.dist-info/METADATA
qrl_graph-0.0.13.dist-info/WHEEL
qrl_graph-0.0.13.dist-info/top_level.txt
qrl_graph-0.0.13.dist-info/RECORD
